{
  "data": {
    "article": {},
    "attachments": {},
    "author_id": "1567203042872926208",
    "conversation_id": "2043693183008465382",
    "created_at": "2026-04-14T09:13:13.000Z",
    "edit_controls": {
      "editable_until": "2026-04-14T10:13:13.000Z",
      "edits_remaining": 5,
      "is_edit_eligible": false
    },
    "edit_history_tweet_ids": [
      "2043980888992821534"
    ],
    "entities": {
      "mentions": [
        {
          "end": 16,
          "id": "2043683721992425472",
          "start": 0,
          "username": "OverdoseScholar"
        }
      ]
    },
    "geo": {},
    "id": "2043980888992821534",
    "in_reply_to_user_id": "2043683721992425472",
    "lang": "zh",
    "note_tweet": {
      "entities": {}
    },
    "possibly_sensitive": false,
    "public_metrics": {
      "bookmark_count": 0,
      "impression_count": 0,
      "like_count": 0,
      "quote_count": 0,
      "reply_count": 0,
      "retweet_count": 0
    },
    "referenced_tweets": [
      {
        "id": "2043693183008465382",
        "type": "replied_to"
      }
    ],
    "reply_settings": "everyone",
    "text": "@OverdoseScholar os还能活？！"
  },
  "includes": {
    "media": [
      {
        "alt_text": "The logo of OverdoseScholar Wiki",
        "height": 1024,
        "media_key": "3_2043693159826538496",
        "public_metrics": {},
        "type": "photo",
        "url": "https://pbs.twimg.com/media/HFyoGdVbQAAR9Rx.jpg",
        "width": 1024
      }
    ],
    "tweets": [
      {
        "article": {},
        "attachments": {},
        "author_id": "1567203042872926208",
        "conversation_id": "2043693183008465382",
        "created_at": "2026-04-14T09:13:13.000Z",
        "edit_controls": {
          "editable_until": "2026-04-14T10:13:13.000Z",
          "edits_remaining": 5,
          "is_edit_eligible": false
        },
        "edit_history_tweet_ids": [
          "2043980888992821534"
        ],
        "entities": {
          "mentions": [
            {
              "end": 16,
              "id": "2043683721992425472",
              "start": 0,
              "username": "OverdoseScholar"
            }
          ]
        },
        "geo": {},
        "id": "2043980888992821534",
        "in_reply_to_user_id": "2043683721992425472",
        "lang": "zh",
        "note_tweet": {
          "entities": {}
        },
        "possibly_sensitive": false,
        "public_metrics": {
          "bookmark_count": 0,
          "impression_count": 0,
          "like_count": 0,
          "quote_count": 0,
          "reply_count": 0,
          "retweet_count": 0
        },
        "referenced_tweets": [
          {
            "id": "2043693183008465382",
            "type": "replied_to"
          }
        ],
        "reply_settings": "everyone",
        "text": "@OverdoseScholar os还能活？！"
      },
      {
        "article": {},
        "attachments": {
          "media_keys": [
            "3_2043693159826538496"
          ]
        },
        "author_id": "2043683721992425472",
        "conversation_id": "2043693183008465382",
        "created_at": "2026-04-13T14:09:59.000Z",
        "edit_controls": {
          "editable_until": "2026-04-13T15:09:59.000Z",
          "edits_remaining": 5,
          "is_edit_eligible": true
        },
        "edit_history_tweet_ids": [
          "2043693183008465382"
        ],
        "entities": {
          "urls": [
            {
              "display_url": "pic.x.com/0TgIWkFu7S",
              "end": 187,
              "expanded_url": "https://x.com/OverdoseScholar/status/2043693183008465382/photo/1",
              "media_key": "3_2043693159826538496",
              "start": 164,
              "url": "https://t.co/0TgIWkFu7S"
            }
          ]
        },
        "geo": {},
        "id": "2043693183008465382",
        "lang": "zh",
        "note_tweet": {
          "entities": {}
        },
        "possibly_sensitive": false,
        "public_metrics": {
          "bookmark_count": 0,
          "impression_count": 155,
          "like_count": 9,
          "quote_count": 0,
          "reply_count": 3,
          "retweet_count": 3
        },
        "reply_settings": "everyone",
        "text": "中文OD圈的大家好～\n\n这里是OverdoseScholar Wiki （简称OS Wiki）！\n\n我们的目标是提供符合循证医学的、科学与可证伪的精神药物——尤其是易消遣性使用药物——的信息。本wiki所有信息都将标注参考文献并按照基于OCEBM进行简化与拓展的证据评级体系进行分级，力求传递既不污名化又不神化药物的科学信息！ https://t.co/0TgIWkFu7S"
      }
    ],
    "users": [
      {
        "created_at": "2022-09-06T17:28:25.000Z",
        "description": "别说完蛋这种话！/ 里推@Aki_MountainE\n旧名义：仿生喹硫平/\n梨❤️@Eternal1uv9/\n渡 ⛵️@noth1nghere14/\n♠️🅰️@w0sh1Asak1 /\n聖 🍜@shungleemain /\n提问：https://t.co/IopkqyzpO2",
        "entities": {
          "description": {
            "mentions": [
              {
                "end": 26,
                "start": 12,
                "username": "Aki_MountainE"
              },
              {
                "end": 53,
                "start": 41,
                "username": "Eternal1uv9"
              },
              {
                "end": 73,
                "start": 59,
                "username": "noth1nghere14"
              },
              {
                "end": 90,
                "start": 79,
                "username": "w0sh1Asak1"
              },
              {
                "end": 109,
                "start": 96,
                "username": "shungleemain"
              }
            ],
            "urls": [
              {
                "display_url": "ngl.link/akinoyo",
                "end": 138,
                "expanded_url": "https://ngl.link/akinoyo",
                "start": 115,
                "url": "https://t.co/IopkqyzpO2"
              }
            ]
          },
          "url": {
            "urls": [
              {
                "display_url": "psydrugs.org",
                "end": 23,
                "expanded_url": "http://psydrugs.org",
                "start": 0,
                "url": "https://t.co/bYHkyXl80J"
              }
            ]
          }
        },
        "id": "1567203042872926208",
        "location": "偉大的天國",
        "name": "AkiNoYo！",
        "pinned_tweet_id": "1992482113288057078",
        "profile_image_url": "https://pbs.twimg.com/profile_images/2040976214756843520/I0deaB8C_normal.jpg",
        "protected": false,
        "public_metrics": {
          "followers_count": 882,
          "following_count": 877,
          "like_count": 4037,
          "listed_count": 1,
          "media_count": 119,
          "tweet_count": 1281
        },
        "url": "https://t.co/bYHkyXl80J",
        "username": "Akinoyo_desu",
        "verified": true
      },
      {
        "created_at": "2026-04-13T13:33:50.000Z",
        "description": "Encyclopedia of Evidence-Based Psychopharmacology\n(基于循证医学的精神药物百科) \ne-Mail: OverdoseScholar@outlook.com",
        "entities": {
          "url": {
            "urls": [
              {
                "display_url": "t.me/OverdoseSchola…",
                "end": 23,
                "expanded_url": "https://t.me/OverdoseScholarWiki",
                "start": 0,
                "url": "https://t.co/UEc7ovR0E9"
              }
            ]
          }
        },
        "id": "2043683721992425472",
        "location": "Your Default Mode Network(DMN)",
        "name": "OverdoseScholar Wiki",
        "pinned_tweet_id": "2043693183008465382",
        "profile_image_url": "https://pbs.twimg.com/profile_images/2043684309215891456/VGOEIg4N_normal.jpg",
        "protected": false,
        "public_metrics": {
          "followers_count": 7,
          "following_count": 6,
          "like_count": 13,
          "listed_count": 0,
          "media_count": 1,
          "tweet_count": 1
        },
        "url": "https://t.co/UEc7ovR0E9",
        "username": "OverdoseScholar",
        "verified": false
      }
    ]
  }
}