{
  "data": {
    "article": {},
    "attachments": {},
    "author_id": "1567203042872926208",
    "conversation_id": "2025336542462689328",
    "created_at": "2026-02-21T22:34:02.000Z",
    "edit_controls": {
      "editable_until": "2026-02-21T23:34:02.000Z",
      "edits_remaining": 5,
      "is_edit_eligible": false
    },
    "edit_history_tweet_ids": [
      "2025338248239952203"
    ],
    "entities": {
      "mentions": [
        {
          "end": 12,
          "id": "1878681729407356928",
          "start": 0,
          "username": "HYuusui1999"
        }
      ]
    },
    "geo": {},
    "id": "2025338248239952203",
    "in_reply_to_user_id": "1878681729407356928",
    "lang": "zh",
    "note_tweet": {
      "entities": {}
    },
    "possibly_sensitive": false,
    "public_metrics": {
      "bookmark_count": 0,
      "impression_count": 0,
      "like_count": 0,
      "quote_count": 0,
      "reply_count": 0,
      "retweet_count": 0
    },
    "referenced_tweets": [
      {
        "id": "2025336542462689328",
        "type": "replied_to"
      }
    ],
    "reply_settings": "everyone",
    "text": "@HYuusui1999 他吗的这是鸡哥"
  },
  "includes": {
    "tweets": [
      {
        "article": {},
        "attachments": {},
        "author_id": "1567203042872926208",
        "conversation_id": "2025336542462689328",
        "created_at": "2026-02-21T22:34:02.000Z",
        "edit_controls": {
          "editable_until": "2026-02-21T23:34:02.000Z",
          "edits_remaining": 5,
          "is_edit_eligible": false
        },
        "edit_history_tweet_ids": [
          "2025338248239952203"
        ],
        "entities": {
          "mentions": [
            {
              "end": 12,
              "id": "1878681729407356928",
              "start": 0,
              "username": "HYuusui1999"
            }
          ]
        },
        "geo": {},
        "id": "2025338248239952203",
        "in_reply_to_user_id": "1878681729407356928",
        "lang": "zh",
        "note_tweet": {
          "entities": {}
        },
        "possibly_sensitive": false,
        "public_metrics": {
          "bookmark_count": 0,
          "impression_count": 0,
          "like_count": 0,
          "quote_count": 0,
          "reply_count": 0,
          "retweet_count": 0
        },
        "referenced_tweets": [
          {
            "id": "2025336542462689328",
            "type": "replied_to"
          }
        ],
        "reply_settings": "everyone",
        "text": "@HYuusui1999 他吗的这是鸡哥"
      },
      {
        "article": {},
        "attachments": {},
        "author_id": "1878681729407356928",
        "conversation_id": "2025336542462689328",
        "created_at": "2026-02-21T22:27:15.000Z",
        "edit_controls": {
          "editable_until": "2026-02-21T23:27:15.000Z",
          "edits_remaining": 5,
          "is_edit_eligible": true
        },
        "edit_history_tweet_ids": [
          "2025336542462689328"
        ],
        "entities": {
          "urls": [
            {
              "display_url": "x.com/fayoubaike000/…",
              "end": 34,
              "expanded_url": "https://twitter.com/fayoubaike000/status/2025264317348937809",
              "start": 11,
              "url": "https://t.co/OpjXTIWwFu"
            }
          ]
        },
        "geo": {},
        "id": "2025336542462689328",
        "lang": "zh",
        "note_tweet": {
          "entities": {}
        },
        "possibly_sensitive": false,
        "public_metrics": {
          "bookmark_count": 0,
          "impression_count": 9,
          "like_count": 0,
          "quote_count": 0,
          "reply_count": 1,
          "retweet_count": 0
        },
        "referenced_tweets": [
          {
            "id": "2025264317348937809",
            "type": "quoted"
          }
        ],
        "reply_settings": "everyone",
        "text": "请问谁有此人相关信息 https://t.co/OpjXTIWwFu"
      }
    ],
    "users": [
      {
        "created_at": "2022-09-06T17:28:25.000Z",
        "description": "别说完蛋这种话！/ 旧名义：仿生喹硫平/ 涘🧊@winterfruit_1 /聖 🍜@shungleemain /♠️🅰️@w0sh1Asak1 /渡 🚣‍♂️@justyanwu14/提问：https://t.co/IopkqyzpO2",
        "entities": {
          "description": {
            "mentions": [
              {
                "end": 37,
                "start": 23,
                "username": "winterfruit_1"
              },
              {
                "end": 55,
                "start": 42,
                "username": "shungleemain"
              },
              {
                "end": 72,
                "start": 61,
                "username": "w0sh1Asak1"
              },
              {
                "end": 92,
                "start": 80,
                "username": "justyanwu14"
              }
            ],
            "urls": [
              {
                "display_url": "ngl.link/akinoyo",
                "end": 119,
                "expanded_url": "https://ngl.link/akinoyo",
                "start": 96,
                "url": "https://t.co/IopkqyzpO2"
              }
            ]
          },
          "url": {
            "urls": [
              {
                "display_url": "psydrugs.org",
                "end": 23,
                "expanded_url": "http://psydrugs.org",
                "start": 0,
                "url": "https://t.co/bYHkyXl80J"
              }
            ]
          }
        },
        "id": "1567203042872926208",
        "location": "偉大的天國",
        "name": "Akino5150#海山二",
        "pinned_tweet_id": "1992482113288057078",
        "profile_image_url": "https://pbs.twimg.com/profile_images/2011689303659986945/O3P_h217_normal.jpg",
        "protected": false,
        "public_metrics": {
          "followers_count": 445,
          "following_count": 688,
          "like_count": 2509,
          "listed_count": 1,
          "media_count": 86,
          "tweet_count": 757
        },
        "url": "https://t.co/bYHkyXl80J",
        "username": "Akinoyo_desu",
        "verified": false
      },
      {
        "created_at": "2025-01-13T05:53:31.000Z",
        "description": "「等待並心懷希望吧。」希望大家都好好生活。\n\n理想鄉：@t_subas_a\n\n拜託各位看到任何通知的幫忙轉貼謝啦",
        "entities": {
          "description": {
            "mentions": [
              {
                "end": 37,
                "start": 27,
                "username": "t_subas_a"
              }
            ]
          },
          "url": {
            "urls": [
              {
                "display_url": "bilibili.com/video/BV1oW411…",
                "end": 23,
                "expanded_url": "https://www.bilibili.com/video/BV1oW411b7hx/",
                "start": 0,
                "url": "https://t.co/BjaOJfWZqU"
              }
            ]
          }
        },
        "id": "1878681729407356928",
        "location": "人間邊緣",
        "name": "祐穂・H",
        "pinned_tweet_id": "1921895055087841673",
        "profile_image_url": "https://pbs.twimg.com/profile_images/1878962553587433472/IIEZXezB_normal.jpg",
        "protected": false,
        "public_metrics": {
          "followers_count": 1068,
          "following_count": 2992,
          "like_count": 43671,
          "listed_count": 6,
          "media_count": 364,
          "tweet_count": 10941
        },
        "url": "https://t.co/BjaOJfWZqU",
        "username": "HYuusui1999",
        "verified": false
      }
    ]
  }
}