{
  "data": {
    "article": {},
    "attachments": {},
    "author_id": "1567203042872926208",
    "conversation_id": "2037581466792857693",
    "created_at": "2026-03-27T18:58:23.000Z",
    "edit_controls": {
      "editable_until": "2026-03-27T19:58:23.000Z",
      "edits_remaining": 5,
      "is_edit_eligible": false
    },
    "edit_history_tweet_ids": [
      "2037605165977764326"
    ],
    "entities": {
      "mentions": [
        {
          "end": 13,
          "id": "1888428282192039936",
          "start": 0,
          "username": "babystar1204"
        }
      ]
    },
    "geo": {},
    "id": "2037605165977764326",
    "in_reply_to_user_id": "1888428282192039936",
    "lang": "qme",
    "note_tweet": {
      "entities": {}
    },
    "possibly_sensitive": false,
    "public_metrics": {
      "bookmark_count": 0,
      "impression_count": 0,
      "like_count": 0,
      "quote_count": 0,
      "reply_count": 0,
      "retweet_count": 0
    },
    "referenced_tweets": [
      {
        "id": "2037581466792857693",
        "type": "replied_to"
      }
    ],
    "reply_settings": "everyone",
    "text": "@babystar1204 🥵"
  },
  "includes": {
    "tweets": [
      {
        "article": {},
        "attachments": {},
        "author_id": "1567203042872926208",
        "conversation_id": "2037581466792857693",
        "created_at": "2026-03-27T18:58:23.000Z",
        "edit_controls": {
          "editable_until": "2026-03-27T19:58:23.000Z",
          "edits_remaining": 5,
          "is_edit_eligible": false
        },
        "edit_history_tweet_ids": [
          "2037605165977764326"
        ],
        "entities": {
          "mentions": [
            {
              "end": 13,
              "id": "1888428282192039936",
              "start": 0,
              "username": "babystar1204"
            }
          ]
        },
        "geo": {},
        "id": "2037605165977764326",
        "in_reply_to_user_id": "1888428282192039936",
        "lang": "qme",
        "note_tweet": {
          "entities": {}
        },
        "possibly_sensitive": false,
        "public_metrics": {
          "bookmark_count": 0,
          "impression_count": 0,
          "like_count": 0,
          "quote_count": 0,
          "reply_count": 0,
          "retweet_count": 0
        },
        "referenced_tweets": [
          {
            "id": "2037581466792857693",
            "type": "replied_to"
          }
        ],
        "reply_settings": "everyone",
        "text": "@babystar1204 🥵"
      },
      {
        "article": {},
        "attachments": {},
        "author_id": "1888428282192039936",
        "conversation_id": "2037581466792857693",
        "created_at": "2026-03-27T17:24:12.000Z",
        "edit_controls": {
          "editable_until": "2026-03-27T18:24:12.000Z",
          "edits_remaining": 5,
          "is_edit_eligible": true
        },
        "edit_history_tweet_ids": [
          "2037581466792857693"
        ],
        "entities": {},
        "geo": {},
        "id": "2037581466792857693",
        "lang": "zh",
        "note_tweet": {
          "entities": {}
        },
        "possibly_sensitive": false,
        "public_metrics": {
          "bookmark_count": 0,
          "impression_count": 23,
          "like_count": 1,
          "quote_count": 0,
          "reply_count": 1,
          "retweet_count": 0
        },
        "reply_settings": "everyone",
        "text": "自从和贡共用他的音乐vip我直接把自己的续费取消了\n现在最爱干的事就是听他的历史播放幻想自己就是他"
      }
    ],
    "users": [
      {
        "created_at": "2022-09-06T17:28:25.000Z",
        "description": "别说完蛋这种话！/ \n旧名义：仿生喹硫平/\n梨❤️@Eternal1uv9/\n涘🧊@winterfruit_1 /\n渡 🚣‍♂️@noth1nghere14/\n♠️🅰️@w0sh1Asak1 /\n聖 🍜@shungleemain /\n提问：https://t.co/IopkqyzpO2",
        "entities": {
          "description": {
            "mentions": [
              {
                "end": 37,
                "start": 25,
                "username": "Eternal1uv9"
              },
              {
                "end": 55,
                "start": 41,
                "username": "winterfruit_1"
              },
              {
                "end": 78,
                "start": 64,
                "username": "noth1nghere14"
              },
              {
                "end": 95,
                "start": 84,
                "username": "w0sh1Asak1"
              },
              {
                "end": 114,
                "start": 101,
                "username": "shungleemain"
              }
            ],
            "urls": [
              {
                "display_url": "ngl.link/akinoyo",
                "end": 143,
                "expanded_url": "https://ngl.link/akinoyo",
                "start": 120,
                "url": "https://t.co/IopkqyzpO2"
              }
            ]
          },
          "url": {
            "urls": [
              {
                "display_url": "psydrugs.org",
                "end": 23,
                "expanded_url": "http://psydrugs.org",
                "start": 0,
                "url": "https://t.co/bYHkyXl80J"
              }
            ]
          }
        },
        "id": "1567203042872926208",
        "location": "偉大的天國",
        "name": "Akino5150#海山二",
        "pinned_tweet_id": "1992482113288057078",
        "profile_image_url": "https://pbs.twimg.com/profile_images/2011689303659986945/O3P_h217_normal.jpg",
        "protected": false,
        "public_metrics": {
          "followers_count": 851,
          "following_count": 865,
          "like_count": 3689,
          "listed_count": 1,
          "media_count": 103,
          "tweet_count": 1106
        },
        "url": "https://t.co/bYHkyXl80J",
        "username": "Akinoyo_desu",
        "verified": true
      },
      {
        "created_at": "2025-02-09T03:22:53.000Z",
        "description": "@dddlg28 让我们一起拥有一个无尽的梦想吧",
        "entities": {
          "description": {
            "mentions": [
              {
                "end": 8,
                "start": 0,
                "username": "dddlg28"
              }
            ]
          }
        },
        "id": "1888428282192039936",
        "location": "审判",
        "name": "永诗一",
        "pinned_tweet_id": "2036080668086845524",
        "profile_image_url": "https://pbs.twimg.com/profile_images/2037382250741035008/ItkWlcKb_normal.jpg",
        "protected": false,
        "public_metrics": {
          "followers_count": 53,
          "following_count": 47,
          "like_count": 430,
          "listed_count": 1,
          "media_count": 80,
          "tweet_count": 437
        },
        "username": "babystar1204",
        "verified": false
      }
    ]
  }
}