{
  "data": {
    "article": {},
    "attachments": {
      "media_keys": [
        "3_2009008953032888323"
      ]
    },
    "author_id": "1567203042872926208",
    "conversation_id": "2009008961069232358",
    "created_at": "2026-01-07T21:07:16.000Z",
    "edit_controls": {
      "editable_until": "2026-01-07T22:07:16.000Z",
      "edits_remaining": 5,
      "is_edit_eligible": true
    },
    "edit_history_tweet_ids": [
      "2009008961069232358"
    ],
    "entities": {
      "urls": [
        {
          "display_url": "pic.x.com/wAeejftYmI",
          "end": 37,
          "expanded_url": "https://x.com/Akinoyo_desu/status/2009008961069232358/photo/1",
          "media_key": "3_2009008953032888323",
          "start": 14,
          "url": "https://t.co/wAeejftYmI"
        }
      ]
    },
    "geo": {},
    "id": "2009008961069232358",
    "lang": "zh",
    "note_tweet": {
      "entities": {}
    },
    "possibly_sensitive": false,
    "public_metrics": {
      "bookmark_count": 0,
      "impression_count": 0,
      "like_count": 0,
      "quote_count": 0,
      "reply_count": 0,
      "retweet_count": 0
    },
    "reply_settings": "everyone",
    "text": "谢谢你！！！！！🥰🥰🥰🥰🥰 https://t.co/wAeejftYmI"
  },
  "includes": {
    "media": [
      {
        "height": 2048,
        "media_key": "3_2009008953032888323",
        "public_metrics": {},
        "type": "photo",
        "url": "https://pbs.twimg.com/media/G-Fu_6Qa0AMSvSb.jpg",
        "width": 942
      }
    ],
    "tweets": [
      {
        "article": {},
        "attachments": {
          "media_keys": [
            "3_2009008953032888323"
          ]
        },
        "author_id": "1567203042872926208",
        "conversation_id": "2009008961069232358",
        "created_at": "2026-01-07T21:07:16.000Z",
        "edit_controls": {
          "editable_until": "2026-01-07T22:07:16.000Z",
          "edits_remaining": 5,
          "is_edit_eligible": true
        },
        "edit_history_tweet_ids": [
          "2009008961069232358"
        ],
        "entities": {
          "urls": [
            {
              "display_url": "pic.x.com/wAeejftYmI",
              "end": 37,
              "expanded_url": "https://x.com/Akinoyo_desu/status/2009008961069232358/photo/1",
              "media_key": "3_2009008953032888323",
              "start": 14,
              "url": "https://t.co/wAeejftYmI"
            }
          ]
        },
        "geo": {},
        "id": "2009008961069232358",
        "lang": "zh",
        "note_tweet": {
          "entities": {}
        },
        "possibly_sensitive": false,
        "public_metrics": {
          "bookmark_count": 0,
          "impression_count": 0,
          "like_count": 0,
          "quote_count": 0,
          "reply_count": 0,
          "retweet_count": 0
        },
        "reply_settings": "everyone",
        "text": "谢谢你！！！！！🥰🥰🥰🥰🥰 https://t.co/wAeejftYmI"
      }
    ],
    "users": [
      {
        "created_at": "2022-09-06T17:28:25.000Z",
        "description": "别说完蛋这种话！/提问：https://t.co/IopkqyzpO2",
        "entities": {
          "description": {
            "urls": [
              {
                "display_url": "ngl.link/akinoyo",
                "end": 35,
                "expanded_url": "https://ngl.link/akinoyo",
                "start": 12,
                "url": "https://t.co/IopkqyzpO2"
              }
            ]
          }
        },
        "id": "1567203042872926208",
        "name": "喹硫平归来！",
        "pinned_tweet_id": "1992482113288057078",
        "profile_image_url": "https://pbs.twimg.com/profile_images/2008853934237265920/Esn-Ry5h_normal.jpg",
        "protected": false,
        "public_metrics": {
          "followers_count": 333,
          "following_count": 520,
          "like_count": 1329,
          "listed_count": 0,
          "media_count": 50,
          "tweet_count": 491
        },
        "username": "Akinoyo_desu",
        "verified": false
      }
    ]
  }
}