{
  "data": {
    "article": {},
    "attachments": {},
    "author_id": "1567203042872926208",
    "conversation_id": "2046509242275037312",
    "created_at": "2026-04-21T14:37:06.000Z",
    "edit_controls": {
      "editable_until": "2026-04-21T15:37:06.000Z",
      "edits_remaining": 5,
      "is_edit_eligible": false
    },
    "edit_history_tweet_ids": [
      "2046599109902221648"
    ],
    "entities": {
      "mentions": [
        {
          "end": 12,
          "id": "2029908828125548546",
          "start": 0,
          "username": "bui_tu46916"
        }
      ]
    },
    "geo": {},
    "id": "2046599109902221648",
    "in_reply_to_user_id": "2029908828125548546",
    "lang": "zh",
    "note_tweet": {
      "entities": {}
    },
    "possibly_sensitive": false,
    "public_metrics": {
      "bookmark_count": 0,
      "impression_count": 0,
      "like_count": 0,
      "quote_count": 0,
      "reply_count": 0,
      "retweet_count": 0
    },
    "referenced_tweets": [
      {
        "id": "2046509242275037312",
        "type": "replied_to"
      }
    ],
    "reply_settings": "everyone",
    "text": "@bui_tu46916 五年以后还可以多o点布洛芬等待肝衰竭死亡"
  },
  "includes": {
    "tweets": [
      {
        "article": {},
        "attachments": {},
        "author_id": "1567203042872926208",
        "conversation_id": "2046509242275037312",
        "created_at": "2026-04-21T14:37:06.000Z",
        "edit_controls": {
          "editable_until": "2026-04-21T15:37:06.000Z",
          "edits_remaining": 5,
          "is_edit_eligible": false
        },
        "edit_history_tweet_ids": [
          "2046599109902221648"
        ],
        "entities": {
          "mentions": [
            {
              "end": 12,
              "id": "2029908828125548546",
              "start": 0,
              "username": "bui_tu46916"
            }
          ]
        },
        "geo": {},
        "id": "2046599109902221648",
        "in_reply_to_user_id": "2029908828125548546",
        "lang": "zh",
        "note_tweet": {
          "entities": {}
        },
        "possibly_sensitive": false,
        "public_metrics": {
          "bookmark_count": 0,
          "impression_count": 0,
          "like_count": 0,
          "quote_count": 0,
          "reply_count": 0,
          "retweet_count": 0
        },
        "referenced_tweets": [
          {
            "id": "2046509242275037312",
            "type": "replied_to"
          }
        ],
        "reply_settings": "everyone",
        "text": "@bui_tu46916 五年以后还可以多o点布洛芬等待肝衰竭死亡"
      },
      {
        "article": {},
        "attachments": {},
        "author_id": "2029908828125548546",
        "conversation_id": "2046509242275037312",
        "created_at": "2026-04-21T08:40:00.000Z",
        "edit_controls": {
          "editable_until": "2026-04-21T09:40:00.000Z",
          "edits_remaining": 5,
          "is_edit_eligible": true
        },
        "edit_history_tweet_ids": [
          "2046509242275037312"
        ],
        "entities": {},
        "geo": {},
        "id": "2046509242275037312",
        "lang": "zh",
        "note_tweet": {
          "entities": {}
        },
        "possibly_sensitive": false,
        "public_metrics": {
          "bookmark_count": 1,
          "impression_count": 3684,
          "like_count": 52,
          "quote_count": 4,
          "reply_count": 20,
          "retweet_count": 1
        },
        "reply_settings": "everyone",
        "text": "5年，5年以后o圈还有什么？"
      }
    ],
    "users": [
      {
        "created_at": "2022-09-06T17:28:25.000Z",
        "description": "别说完蛋这种话！/ 旧名义：仿生喹硫平\n里帐@Aki_MountainE\n梨❤️@Eternal1uv9/@SummerTWT9\n聖 🍜@shungleemain /\n渡 ⛵️@noth1nghere14/\n💧🍐 @kikunashi30712/\n♠️🅰️@w0sh1Asak1 /",
        "entities": {
          "description": {
            "mentions": [
              {
                "end": 36,
                "start": 22,
                "username": "Aki_MountainE"
              },
              {
                "end": 52,
                "start": 40,
                "username": "Eternal1uv9"
              },
              {
                "end": 64,
                "start": 53,
                "username": "SummerTWT9"
              },
              {
                "end": 81,
                "start": 68,
                "username": "shungleemain"
              },
              {
                "end": 102,
                "start": 88,
                "username": "noth1nghere14"
              },
              {
                "end": 122,
                "start": 107,
                "username": "kikunashi30712"
              },
              {
                "end": 139,
                "start": 128,
                "username": "w0sh1Asak1"
              }
            ]
          },
          "url": {
            "urls": [
              {
                "display_url": "psydrugs.org",
                "end": 23,
                "expanded_url": "http://psydrugs.org",
                "start": 0,
                "url": "https://t.co/bYHkyXl80J"
              }
            ]
          }
        },
        "id": "1567203042872926208",
        "location": "偉大的天國",
        "name": "AkiNoYo！",
        "profile_image_url": "https://pbs.twimg.com/profile_images/2040976214756843520/I0deaB8C_normal.jpg",
        "protected": false,
        "public_metrics": {
          "followers_count": 897,
          "following_count": 903,
          "like_count": 4216,
          "listed_count": 1,
          "media_count": 122,
          "tweet_count": 1344
        },
        "url": "https://t.co/bYHkyXl80J",
        "username": "Akinoyo_desu",
        "verified": true
      },
      {
        "created_at": "2026-03-06T13:16:07.000Z",
        "description": "你好",
        "id": "2029908828125548546",
        "location": "普瑞巴林行动小组",
        "name": "EXPcat",
        "profile_image_url": "https://pbs.twimg.com/profile_images/2040793488061861888/h0unB2hS_normal.jpg",
        "protected": false,
        "public_metrics": {
          "followers_count": 234,
          "following_count": 202,
          "like_count": 170,
          "listed_count": 0,
          "media_count": 24,
          "tweet_count": 605
        },
        "username": "bui_tu46916",
        "verified": false
      }
    ]
  }
}